mlfinpy/__init__.py
mlfinpy/cross_validation/__init__.py
mlfinpy/cross_validation/combinatorial.py
mlfinpy/cross_validation/cross_validation.py
mlfinpy/data_structure/__init__.py
mlfinpy/data_structure/base_bars.py
mlfinpy/data_structure/imbalance_bars.py
mlfinpy/data_structure/run_bars.py
mlfinpy/data_structure/standard_bars.py
mlfinpy/data_structure/time_bars.py
mlfinpy/dataset/.DS_Store
mlfinpy/dataset/__init__.py
mlfinpy/dataset/data/dollar_bar_sample.csv
mlfinpy/dataset/data/stock_prices.csv
mlfinpy/dataset/data/tick_data.csv
mlfinpy/dataset/load_datasets.py
mlfinpy/ensemble/__init__.py
mlfinpy/ensemble/sb_bagging.py
mlfinpy/filters/__init__.py
mlfinpy/filters/filters.py
mlfinpy/labeling/__init__.py
mlfinpy/labeling/fixed_time_horizon.py
mlfinpy/labeling/labeling.py
mlfinpy/labeling/raw_return.py
mlfinpy/labeling/trend_scanning.py
mlfinpy/sample_weights/__init__.py
mlfinpy/sample_weights/attribution.py
mlfinpy/sampling/__init__.py
mlfinpy/sampling/bootstrapping.py
mlfinpy/sampling/concurrent.py
mlfinpy/structural_breaks/__init__.py
mlfinpy/structural_breaks/chow.py
mlfinpy/structural_breaks/cusum.py
mlfinpy/structural_breaks/sadf.py
mlfinpy/util/__init__.py
mlfinpy/util/fast_ewma.py
mlfinpy/util/frac_diff.py
mlfinpy/util/generate_dataset.py
mlfinpy/util/helper.py
mlfinpy/util/multiprocess.py
mlfinpy/util/volatility.py
mlfinpy-0.1.2.dist-info/LICENSE
mlfinpy-0.1.2.dist-info/METADATA
mlfinpy-0.1.2.dist-info/WHEEL
mlfinpy-0.1.2.dist-info/RECORD
